license_key/__init__.py
license_key-1.0.4.dist-info/LICENSE
license_key-1.0.4.dist-info/METADATA
license_key-1.0.4.dist-info/WHEEL
license_key-1.0.4.dist-info/entry_points.txt
license_key-1.0.4.dist-info/top_level.txt
license_key-1.0.4.dist-info/RECORD
