Metadata-Version: 2.1
Name: license-key
Version: 1.0.4
Summary: License key managaming for you project
Author-email: marat2509 <marat.budkevich.0000@gmail.com>
License: LICENSE :: OSI APPROVED :: GNU GENERAL PUBLIC LICENSE V3 (GPLV3)
Project-URL: Homepage, https://github.com/marat2509/license-key
Keywords: license key
License-File: LICENSE
Requires-Dist: requires
Requires-Dist: loguru
